{
  "generated_at": "2026-07-10T00:04:30+00:00",
  "total_contacts_seen": 726,
  "total_unique_tankers_in_context_zones": 188,
  "total_tanker_context_zones": 8,
  "neutral_tanker_context_total": 171,
  "voi_tankers_in_context_zones": 17,
  "policy": "Neutral tankers are context-only. They imply no sanctions, Russian link or false-flag status unless another category is present.",
  "zones": [
    {
      "total_tankers": 82,
      "neutral_tankers": 76,
      "voi_tankers": 6,
      "slow_or_waiting": 38,
      "for_order": 4,
      "examples": [
        {
          "name": "SEACOD",
          "imo": "9352315",
          "mmsi": "218019000",
          "destination": "PLSWI",
          "sog": "12.7",
          "categories": [
            "neutral_tanker_context"
          ]
        },
        {
          "name": "SEASHARK",
          "imo": "9298193",
          "mmsi": "211135000",
          "destination": "DK ENS",
          "sog": "10.9",
          "categories": [
            "neutral_tanker_context"
          ]
        },
        {
          "name": "SAANA",
          "imo": "9739836",
          "mmsi": "230706000",
          "destination": "FINLI>SEGOT",
          "sog": "0",
          "categories": [
            "neutral_tanker_context"
          ]
        },
        {
          "name": "OVIT",
          "imo": "9466611",
          "mmsi": "256661000",
          "destination": "NLRTM",
          "sog": "6.4",
          "categories": [
            "neutral_tanker_context"
          ]
        },
        {
          "name": "YARA SELA",
          "imo": "9734850",
          "mmsi": "258936000",
          "destination": "DERSK",
          "sog": "11.5",
          "categories": [
            "neutral_tanker_context"
          ]
        },
        {
          "name": "ALFA ALANDIA",
          "imo": "9752797",
          "mmsi": "311000534",
          "destination": "PLGDN>DKSKA",
          "sog": "8.3",
          "categories": [
            "neutral_tanker_context"
          ]
        },
        {
          "name": "HAIFENG",
          "imo": "9792840",
          "mmsi": "636020805",
          "destination": "FNPRV",
          "sog": "11.5",
          "categories": [
            "neutral_tanker_context"
          ]
        },
        {
          "name": "ECO SORCERER",
          "imo": "9933468",
          "mmsi": "538009926",
          "destination": "RU ULU",
          "sog": "7.7",
          "categories": [
            "recent_russian_portcall_10d"
          ]
        }
      ],
      "zone_id": "danish_straits_kattegat",
      "zone_label": "Danish Straits / Kattegat",
      "level": "heightened_context"
    },
    {
      "total_tankers": 54,
      "neutral_tankers": 53,
      "voi_tankers": 1,
      "slow_or_waiting": 30,
      "for_order": 0,
      "examples": [
        {
          "name": "SEASHARK",
          "imo": "9298193",
          "mmsi": "211135000",
          "destination": "DK ENS",
          "sog": "10.9",
          "categories": [
            "neutral_tanker_context"
          ]
        },
        {
          "name": "SAANA",
          "imo": "9739836",
          "mmsi": "230706000",
          "destination": "FINLI>SEGOT",
          "sog": "0",
          "categories": [
            "neutral_tanker_context"
          ]
        },
        {
          "name": "OVIT",
          "imo": "9466611",
          "mmsi": "256661000",
          "destination": "NLRTM",
          "sog": "6.4",
          "categories": [
            "neutral_tanker_context"
          ]
        },
        {
          "name": "ALFA ALANDIA",
          "imo": "9752797",
          "mmsi": "311000534",
          "destination": "PLGDN>DKSKA",
          "sog": "8.3",
          "categories": [
            "neutral_tanker_context"
          ]
        },
        {
          "name": "P.MASSPORT",
          "imo": "9997476",
          "mmsi": "538011641",
          "destination": "DK KAL",
          "sog": "13.2",
          "categories": [
            "neutral_tanker_context"
          ]
        },
        {
          "name": "BLACK SUNRISE",
          "imo": "9546162",
          "mmsi": "248180000",
          "destination": "EE TLL OPL",
          "sog": "10",
          "categories": [
            "neutral_tanker_context"
          ]
        },
        {
          "name": "PROMETEY",
          "imo": "9832559",
          "mmsi": "273270850",
          "destination": "RUULU",
          "sog": "9.9",
          "categories": [
            "recent_russian_portcall_10d",
            "russian_mmsi",
            "sanctions_shadowfleet",
            "watchlist"
          ]
        },
        {
          "name": "STEN ARNOLD",
          "imo": "9371610",
          "mmsi": "255915983",
          "destination": "SEGOT",
          "sog": "0.2",
          "categories": [
            "neutral_tanker_context"
          ]
        }
      ],
      "zone_id": "skagen_waiting_area",
      "zone_label": "Skagen / northern Kattegat",
      "level": "heightened_context"
    },
    {
      "total_tankers": 42,
      "neutral_tankers": 41,
      "voi_tankers": 1,
      "slow_or_waiting": 17,
      "for_order": 1,
      "examples": [
        {
          "name": "GAS ESCO",
          "imo": "9507752",
          "mmsi": "255916105",
          "destination": "ES CEU",
          "sog": "0",
          "categories": [
            "neutral_tanker_context"
          ]
        },
        {
          "name": "MURRAY STAR",
          "imo": "9527635",
          "mmsi": "215178000",
          "destination": "ES MLN",
          "sog": "13",
          "categories": [
            "neutral_tanker_context"
          ]
        },
        {
          "name": "MULE",
          "imo": "9298662",
          "mmsi": "314842000",
          "destination": "TANGIER/MOROCCO",
          "sog": "0.2",
          "categories": [
            "neutral_tanker_context"
          ]
        },
        {
          "name": "OZDEN THERESA",
          "imo": "9338735",
          "mmsi": "215253000",
          "destination": "ESALG",
          "sog": "8.4",
          "categories": [
            "neutral_tanker_context"
          ]
        },
        {
          "name": "CHEMROAD HAYA",
          "imo": "9303649",
          "mmsi": "354801000",
          "destination": "GI GIB",
          "sog": "7.8",
          "categories": [
            "neutral_tanker_context"
          ]
        },
        {
          "name": "ZAPPHIRE",
          "imo": "9391957",
          "mmsi": "248159000",
          "destination": "MTMAR",
          "sog": "12.8",
          "categories": [
            "neutral_tanker_context"
          ]
        },
        {
          "name": "ASIA UNITY",
          "imo": "9622069",
          "mmsi": "563212200",
          "destination": "ES ALG",
          "sog": "3.2",
          "categories": [
            "neutral_tanker_context"
          ]
        },
        {
          "name": "MINERVA ZEN",
          "imo": "9410909",
          "mmsi": "241190000",
          "destination": "FOR ORDERS",
          "sog": "9.6",
          "categories": [
            "neutral_tanker_context"
          ]
        }
      ],
      "zone_id": "gibraltar_west_med_gateway",
      "zone_label": "Gibraltar / W. Mediterranean gateway",
      "level": "heightened_context"
    },
    {
      "total_tankers": 25,
      "neutral_tankers": 25,
      "voi_tankers": 0,
      "slow_or_waiting": 17,
      "for_order": 1,
      "examples": [
        {
          "name": "BRUNO",
          "imo": "0",
          "mmsi": "244868792",
          "destination": "HARLINGEN",
          "sog": "0",
          "categories": [
            "neutral_tanker_context"
          ]
        },
        {
          "name": "EEMSHAVEN LNG",
          "imo": "9757694",
          "mmsi": "205157000",
          "destination": "",
          "sog": "0",
          "categories": [
            "neutral_tanker_context"
          ]
        },
        {
          "name": "FONIKS SUPPORTER",
          "imo": "8661020",
          "mmsi": "219022047",
          "destination": "ESBJERG",
          "sog": "0",
          "categories": [
            "neutral_tanker_context"
          ]
        },
        {
          "name": "XING HAI WAN",
          "imo": "9570113",
          "mmsi": "371737000",
          "destination": "STEINKJER",
          "sog": "8.3",
          "categories": [
            "neutral_tanker_context"
          ]
        },
        {
          "name": "FINJA",
          "imo": "9212345",
          "mmsi": "211333700",
          "destination": "DEBRV",
          "sog": "9.7",
          "categories": [
            "neutral_tanker_context"
          ]
        },
        {
          "name": "WISBY ARGAN",
          "imo": "9426489",
          "mmsi": "259746000",
          "destination": "NLHAR",
          "sog": "0",
          "categories": [
            "neutral_tanker_context"
          ]
        },
        {
          "name": "DOROTHEA SCHULTE",
          "imo": "9618862",
          "mmsi": "538012341",
          "destination": "NLTZN",
          "sog": "15.4",
          "categories": [
            "neutral_tanker_context"
          ]
        },
        {
          "name": "AMARANTH",
          "imo": "9458028",
          "mmsi": "209507000",
          "destination": "DE BRE",
          "sog": "0",
          "categories": [
            "neutral_tanker_context"
          ]
        }
      ],
      "zone_id": "german_bight",
      "zone_label": "German Bight",
      "level": "watch"
    },
    {
      "total_tankers": 14,
      "neutral_tankers": 14,
      "voi_tankers": 0,
      "slow_or_waiting": 12,
      "for_order": 0,
      "examples": [
        {
          "name": "SONGA AURORA",
          "imo": "9373632",
          "mmsi": "255806341",
          "destination": "PLGDY",
          "sog": "0",
          "categories": [
            "neutral_tanker_context"
          ]
        },
        {
          "name": "AEGEAN NOBILITY",
          "imo": "9345441",
          "mmsi": "240657000",
          "destination": "PL GDN",
          "sog": "0.3",
          "categories": [
            "neutral_tanker_context"
          ]
        },
        {
          "name": "LANCING",
          "imo": "9792046",
          "mmsi": "311000766",
          "destination": "GBHPT>PLGDN",
          "sog": "0",
          "categories": [
            "neutral_tanker_context"
          ]
        },
        {
          "name": "ARETEA",
          "imo": "9711456",
          "mmsi": "241348000",
          "destination": "LYLMQ=>PLGDN",
          "sog": "0",
          "categories": [
            "neutral_tanker_context"
          ]
        },
        {
          "name": "KEY SUND",
          "imo": "8920567",
          "mmsi": "259360000",
          "destination": "PLGDY>GBFTX VIA KIEL",
          "sog": "12.8",
          "categories": [
            "neutral_tanker_context"
          ]
        },
        {
          "name": "ANGON",
          "imo": "9131199",
          "mmsi": "261037120",
          "destination": "PLNOW",
          "sog": "0",
          "categories": [
            "neutral_tanker_context"
          ]
        },
        {
          "name": "ALPES",
          "imo": "9817470",
          "mmsi": "636023942",
          "destination": "NOSTU",
          "sog": "0",
          "categories": [
            "neutral_tanker_context"
          ]
        },
        {
          "name": "STI GUIDE",
          "imo": "9717113",
          "mmsi": "538005823",
          "destination": "PLGDN",
          "sog": "0",
          "categories": [
            "neutral_tanker_context"
          ]
        }
      ],
      "zone_id": "kaliningrad_baltiysk_approaches",
      "zone_label": "Kaliningrad / Baltiysk approaches",
      "level": "watch"
    },
    {
      "total_tankers": 14,
      "neutral_tankers": 14,
      "voi_tankers": 0,
      "slow_or_waiting": 12,
      "for_order": 0,
      "examples": [
        {
          "name": "SONGA AURORA",
          "imo": "9373632",
          "mmsi": "255806341",
          "destination": "PLGDY",
          "sog": "0",
          "categories": [
            "neutral_tanker_context"
          ]
        },
        {
          "name": "AEGEAN NOBILITY",
          "imo": "9345441",
          "mmsi": "240657000",
          "destination": "PL GDN",
          "sog": "0.3",
          "categories": [
            "neutral_tanker_context"
          ]
        },
        {
          "name": "LANCING",
          "imo": "9792046",
          "mmsi": "311000766",
          "destination": "GBHPT>PLGDN",
          "sog": "0",
          "categories": [
            "neutral_tanker_context"
          ]
        },
        {
          "name": "ARETEA",
          "imo": "9711456",
          "mmsi": "241348000",
          "destination": "LYLMQ=>PLGDN",
          "sog": "0",
          "categories": [
            "neutral_tanker_context"
          ]
        },
        {
          "name": "KEY SUND",
          "imo": "8920567",
          "mmsi": "259360000",
          "destination": "PLGDY>GBFTX VIA KIEL",
          "sog": "12.8",
          "categories": [
            "neutral_tanker_context"
          ]
        },
        {
          "name": "ANGON",
          "imo": "9131199",
          "mmsi": "261037120",
          "destination": "PLNOW",
          "sog": "0",
          "categories": [
            "neutral_tanker_context"
          ]
        },
        {
          "name": "ALPES",
          "imo": "9817470",
          "mmsi": "636023942",
          "destination": "NOSTU",
          "sog": "0",
          "categories": [
            "neutral_tanker_context"
          ]
        },
        {
          "name": "STI GUIDE",
          "imo": "9717113",
          "mmsi": "538005823",
          "destination": "PLGDN",
          "sog": "0",
          "categories": [
            "neutral_tanker_context"
          ]
        }
      ],
      "zone_id": "gulf_of_gdansk",
      "zone_label": "Gulf of Gdansk",
      "level": "watch"
    },
    {
      "total_tankers": 15,
      "neutral_tankers": 13,
      "voi_tankers": 2,
      "slow_or_waiting": 5,
      "for_order": 1,
      "examples": [
        {
          "name": "PIS PARAGON",
          "imo": "9403310",
          "mmsi": "563637000",
          "destination": "USNYC FOR ORDER",
          "sog": "11.4",
          "categories": [
            "neutral_tanker_context"
          ]
        },
        {
          "name": "DELTA OCEAN",
          "imo": "9408475",
          "mmsi": "636019889",
          "destination": "OPL GIBRALTAR",
          "sog": "14.6",
          "categories": [
            "neutral_tanker_context"
          ]
        },
        {
          "name": "EVA TOKYO",
          "imo": "9865520",
          "mmsi": "371809000",
          "destination": "GBPTL>GBTHP",
          "sog": "0.2",
          "categories": [
            "neutral_tanker_context"
          ]
        },
        {
          "name": "BOW SEA",
          "imo": "9215282",
          "mmsi": "257894000",
          "destination": "USHOU",
          "sog": "15",
          "categories": [
            "neutral_tanker_context"
          ]
        },
        {
          "name": "NASLEDIE",
          "imo": "9293002",
          "mmsi": "273279840",
          "destination": "EGPSD",
          "sog": "11.5",
          "categories": [
            "russian_mmsi",
            "sanctions_shadowfleet",
            "watchlist"
          ]
        },
        {
          "name": "DURHAM",
          "imo": "9889564",
          "mmsi": "232031864",
          "destination": "NLTNZ-ISHOU",
          "sog": "16.6",
          "categories": [
            "neutral_tanker_context"
          ]
        },
        {
          "name": "RAMANDA",
          "imo": "9739812",
          "mmsi": "266457000",
          "destination": "TOUNGE",
          "sog": "0",
          "categories": [
            "neutral_tanker_context"
          ]
        },
        {
          "name": "SOLAR SKYLER",
          "imo": "9877640",
          "mmsi": "538008706",
          "destination": "ES BCN",
          "sog": "13.4",
          "categories": [
            "neutral_tanker_context"
          ]
        }
      ],
      "zone_id": "dover_channel_gateway",
      "zone_label": "Dover Strait / Channel gateway",
      "level": "heightened_context"
    },
    {
      "total_tankers": 12,
      "neutral_tankers": 4,
      "voi_tankers": 8,
      "slow_or_waiting": 10,
      "for_order": 1,
      "examples": [
        {
          "name": "TEMPEST DREAM",
          "imo": "9308132",
          "mmsi": "667002310",
          "destination": "TALLINN OPL",
          "sog": "",
          "categories": [
            "sanctions_shadowfleet",
            "watchlist"
          ]
        },
        {
          "name": "HALA LIGHT",
          "imo": "9612052",
          "mmsi": "248124000",
          "destination": "FOR ORDERS",
          "sog": "0",
          "categories": [
            "neutral_tanker_context"
          ]
        },
        {
          "name": "STEN BERGEN",
          "imo": "9407988",
          "mmsi": "255915979",
          "destination": "EEMUU",
          "sog": "1.2",
          "categories": [
            "neutral_tanker_context"
          ]
        },
        {
          "name": "ALTIS",
          "imo": "9265756",
          "mmsi": "667002293",
          "destination": "GULF OF FINLAND",
          "sog": "0",
          "categories": [
            "sanctions_shadowfleet",
            "watchlist"
          ]
        },
        {
          "name": "KING PHILIPPOS",
          "imo": "9601194",
          "mmsi": "538009930",
          "destination": "RU ULU",
          "sog": "0",
          "categories": [
            "recent_russian_portcall_10d"
          ]
        },
        {
          "name": "OCEANUS AURORA",
          "imo": "9555008",
          "mmsi": "636021172",
          "destination": "FIPRV",
          "sog": "0",
          "categories": [
            "neutral_tanker_context"
          ]
        },
        {
          "name": "FUXI",
          "imo": "9246463",
          "mmsi": "304218000",
          "destination": "RULED",
          "sog": "0.2",
          "categories": [
            "recent_russian_portcall_10d"
          ]
        },
        {
          "name": "ZENTURO",
          "imo": "9346885",
          "mmsi": "314001093",
          "destination": "BALTIC FOR ORDERS",
          "sog": "0.1",
          "categories": [
            "neutral_tanker_context"
          ]
        }
      ],
      "zone_id": "gulf_of_finland_ru_approaches",
      "zone_label": "Gulf of Finland / Ust-Luga-Primorsk approaches",
      "level": "context"
    }
  ]
}